alluuid/__init__.py
alluuid/uuid_generator.py
alluuid-0.1.1.dist-info/licenses/LICENSE
alluuid-0.1.1.dist-info/METADATA
alluuid-0.1.1.dist-info/WHEEL
alluuid-0.1.1.dist-info/top_level.txt
alluuid-0.1.1.dist-info/RECORD
