Metadata-Version: 2.4
Name: alluuid
Version: 0.1.1
Summary: AllUUID is a versatile Python library for generating universally unique identifiers (UUIDs). It supports multiple versions of UUIDs, including version 1 (time-based), version 4 (random), and version 7 (timestamp-based). This tool is ideal for developers looking to create unique identifiers for databases, session tokens, or any other use cases where uniqueness is critical.
Home-page: https://github.com/krishnatadi/alluuid-pypi
Author: Krishna Tadi
Author-email: 
Classifier: Programming Language :: Python :: 3
Classifier: License :: OSI Approved :: MIT License
Classifier: Operating System :: OS Independent
Requires-Python: >=3.6
License-File: LICENSE
Dynamic: author
Dynamic: classifier
Dynamic: description
Dynamic: description-content-type
Dynamic: home-page
Dynamic: license-file
Dynamic: requires-python
Dynamic: summary
